Workbook

Sheet Summary
A1: IRA 45W commercial clean vehicle tax-credit
B3: Effective Value of Tax Credit
B4: 2025 | C4: 2030 | D4: 2035 & beyond
A5: 45W Heavy Truck Princeton | B5: 40000 | C5: 40000 | D5: 0
A6: 45W Heavy Truck Energy Innovation | B6: 40000 | C6: 40000 | D6: 0
A7: 45W Medium Truck Princeton | B7: 7500 | C7: 7500 | D7: 0
A8: 45W Medium Truck Energy Innovation | B8: 7500 | C8: 7500 | D8: 0
A9: 45W Light Truck Princeton | B9: 7500 | C9: 7500 | D9: 0
A10: 45W Light Truck Energy Innovation | B10: 7500 | C10: 7500 | D10: 0
A12: This tax-credit is for commercial vehicles
A13: no battery sourcing or mineral reuirements
A14: no income requirements
A15: no cost requirements
A16: tax-credit value equals 30% of purchase price or $40,000 for heavy trucks, and $7,500 for medium and light trucks (whichever value is smaller)
A17: Sheet titled "45W calculations" shows that 30% of purchase price is larger than $40,000 for heavy trucks and larger than $7,500 for medium and light trucks

Sheet 45W Calculations
A1: The purpose of this sheet is to calculate non-energy cost (CAPEX and nonCAPEX) to determine whether 30% of cost is larger than the limit for the tax-credit…for all trucks, 30% of cost is larger than limit, so the tax-credit will equal the value of the limit
A3: # Non-fuel cost was adjusted to 1990
A4: # Transportation cost table was mapped from UCD technology to GCAM technology | L4: 45W_tax-credit
A5: region | B5: supplysector | C5: tranSubsector | D5: stub.technology | E5: year | F5: minicam.non.energy.input | G5: input.cost | I5: fcr/(v*g) | J5: Non-energy cost | L5: 0.3 | M5: Limit (all cases)
A6: USA | B6: trn_freight_road | C6: Heavy truck | D6: BEV | E6: 2030 | F6: non-energy | G6: 0.5863 | I6: =J10/(J14*J16) -> 1.2193775e-06 | J6: =G6/I6 -> 480819.09 | L6: =J6*0.3 -> 144245.73 | M6: 40000
A7: USA | B7: trn_freight_road | C7: Light truck | D7: BEV | E7: 2030 | F7: non-energy | G7: 0.1959 | I7: =J10/(J12*J16) -> 4.4693809e-06 | J7: =G7/I7 -> 43831.575 | L7: =J7*0.3 -> 13149.472 | M7: 7500
A8: USA | B8: trn_freight_road | C8: Medium truck | D8: BEV | E8: 2030 | F8: non-energy | G8: 0.435 | I8: =J10/(J13*J16) -> 4.1067524e-06 | J8: =G8/I8 -> 105923.11 | L8: =J8*0.3 -> 31776.934 | M8: 7500
I10: fcr | J10: 0.1627454 | K10: fixed charge rate
I11: v_bus | J11: 51707.82 | K11: vkt_veh_yr
I12: v_LDT | J12: 19574.4 | K12: vkt_veh_yr
I13: v_MDT | J13: 21302.83 | K13: vkt_veh_yr
I14: v_HDT | J14: 71745.99 | K14: vkt_veh_yr
I15: V_LDV | J15: 19204 | K15: vkt_veh_yr
I16: g | J16: ='45W Heavy Truck - GCAM math'!B6 -> 1.8602568 | K16: GDP deflator 2021-1990

Sheet 45W Heavy Truck - GCAM math
A1: IRA 45W heavy-truck tax-credit
A2: Implemented as an add-on file that represents a subsidy (i.e., negative cost) called "IRA_45W_heavy-truck_tax-credit"
A4: Measure | B4: Value | C4: Units | D4: Notes
A5: fcr (10 years) | B5: ='45W Calculations'!J10 -> 0.1627454 | C5: N/A | D5: From gcamdata: energy.DISCOUNT_RATE_VEH + energy.DISCOUNT_RATE_VEH / (((1 + energy.DISCOUNT_RATE_VEH) ^ energy.NPER_AMORT_VEH) - 1)
A6: GDP deflator (2021, 1990) | B6: =118.37 / 63.631 -> 1.8602568 | C6: N/A | D6: From St. Louis Federal Reserve Bank: https://fred.stlouisfed.org/series/A191RD3A086NBEA
A7: Average vehicle-km per year for heavy duty trucks | B7: ='45W Calculations'!J14 -> 71745.99 | C7: vkt/veh/yr | D7: From gcamdata
A8: 2030 subsidy (2021 USD / vehicle) | B8: ='45W Calculations'!M6 -> 40000 | C8: 2021 USD / vehicle | D8: 30% of non-energy cost is greater than the maximum tax-credit, meaning that the cap on the value of the tax credit of $40,000 applies here for heavy duty trucks
A9: 2030 subsidy (1990 USD / vkt) | B9: =B8*B5/B7/B6 -> 0.048775101 | C9: 1990 USD / vkt | D9: S_vkt = S_veh + (fcr / (v*g)), where S_vkt = dollar per vehicle-km traveled subsidy, S_veh = dollar per vehicle subsidy, fcr = fixed charge rate, v = average vkt per year, and g = GDP deflator
A10: 2025 subsidy (2021 USD / vehicle) | B10: =B8 -> 40000 | C10: 2021 USD / vehicle | D10: Same as in 2030
A11: 2025 subsidy (1990 USD / vkt) | B11: =B9/B8*B10 -> 0.048775101 | C11: 1990 USD / vkt | D11: Same as calculation for input value for 2030
A13: GCAM Input for "IRA_45W_heavy-truck_tax-credit" in 2025 | B13: =-B11 -> -0.048775101 | C13: 1990 USD / vkt | D13: This will the same in for all states and DC in GCAM-USA, and the value of the tax-credit will be the same in GCAM-global
A14: GCAM Input for "IRA_45W_heavy-truck_tax-credit" in 2030 | B14: =-B9 -> -0.048775101 | C14: 1990 USD / vkt | D14: This will the same in for all states and DC in GCAM-USA, and the value of the tax-credit will be the same in GCAM-global
A16: * for now, I remove the tax credit after 2032

Sheet 45W Medium Truck - GCAM math
A1: IRA 45W medium-truck tax-credit
A2: Implemented as an add-on file that represents a subsidy (i.e., negative cost) called "IRA_45W_medium-truck_tax-credit"
A4: Measure | B4: Value | C4: Units | D4: Notes
A5: fcr (10 years) | B5: ='45W Calculations'!J10 -> 0.1627454 | C5: N/A | D5: From gcamdata: energy.DISCOUNT_RATE_VEH + energy.DISCOUNT_RATE_VEH / (((1 + energy.DISCOUNT_RATE_VEH) ^ energy.NPER_AMORT_VEH) - 1)
A6: GDP deflator (2021, 1990) | B6: =118.37 / 63.631 -> 1.8602568 | C6: N/A | D6: From St. Louis Federal Reserve Bank: https://fred.stlouisfed.org/series/A191RD3A086NBEA
A7: Average vehicle-km per year for medium duty trucks | B7: ='45W Calculations'!J13 -> 21302.83 | C7: vkt/veh/yr | D7: From gcamdata
A8: 2030 subsidy (2021 USD / vehicle) | B8: 7500 | C8: 2021 USD / vehicle | D8: 30% of non-energy cost is greater than the maximum tax-credit, meaning that the cap on the value of the tax credit of $7,500 applies here for medium duty trucks
A9: 2030 subsidy (1990 USD / vkt) | B9: =B8*B5/B7/B6 -> 0.030800643 | C9: 1990 USD / vkt | D9: S_vkt = S_veh + (fcr / (v*g)), where S_vkt = dollar per vehicle-km traveled subsidy, S_veh = dollar per vehicle subsidy, fcr = fixed charge rate, v = average vkt per year, and g = GDP deflator
A10: 2025 subsidy (2021 USD / vehicle) | B10: =B8 -> 7500 | C10: 2021 USD / vehicle | D10: Same as in 2030
A11: 2025 subsidy (1990 USD / vkt) | B11: =B9/B8*B10 -> 0.030800643 | C11: 1990 USD / vkt | D11: Same as calculation for input value for 2030
A13: GCAM Input for "IRA_45W_medium-truck_tax-credit" in 2025 | B13: =-B11 -> -0.030800643 | C13: 1990 USD / vkt | D13: This will the same in for all states and DC in GCAM-USA, and the value of the tax-credit will be the same in GCAM-global
A14: GCAM Input for "IRA_45W_medium-truck_tax-credit" in 2030 | B14: =-B9 -> -0.030800643 | C14: 1990 USD / vkt | D14: This will the same in for all states and DC in GCAM-USA, and the value of the tax-credit will be the same in GCAM-global
A16: * for now, I remove the tax credit after 2032

Sheet 45W Light Truck - GCAM math
A1: IRA 45W light-truck tax-credit
A2: Implemented as an add-on file that represents a subsidy (i.e., negative cost) called "IRA_45W_light-truck_tax-credit"
A4: Measure | B4: Value | C4: Units | D4: Notes
A5: fcr (10 years) | B5: ='45W Calculations'!J10 -> 0.1627454 | C5: N/A | D5: From gcamdata: energy.DISCOUNT_RATE_VEH + energy.DISCOUNT_RATE_VEH / (((1 + energy.DISCOUNT_RATE_VEH) ^ energy.NPER_AMORT_VEH) - 1)
A6: GDP deflator (2021, 1990) | B6: =118.37 / 63.631 -> 1.8602568 | C6: N/A | D6: From St. Louis Federal Reserve Bank: https://fred.stlouisfed.org/series/A191RD3A086NBEA
A7: Average vehicle-km per year for light duty trucks | B7: ='45W Calculations'!J12 -> 19574.4 | C7: vkt/veh/yr | D7: From gcamdata
A8: 2030 subsidy (2021 USD / vehicle) | B8: 7500 | C8: 2021 USD / vehicle | D8: 30% of non-energy cost is greater than the maximum tax-credit, meaning that the cap on the value of the tax credit of $7,500 applies here for light duty trucks
A9: 2030 subsidy (1990 USD / vkt) | B9: =B8*B5/B7/B6 -> 0.033520356 | C9: 1990 USD / vkt | D9: S_vkt = S_veh + (fcr / (v*g)), where S_vkt = dollar per vehicle-km traveled subsidy, S_veh = dollar per vehicle subsidy, fcr = fixed charge rate, v = average vkt per year, and g = GDP deflator
A10: 2025 subsidy (2021 USD / vehicle) | B10: =B8 -> 7500 | C10: 2021 USD / vehicle | D10: Same as in 2030
A11: 2025 subsidy (1990 USD / vkt) | B11: =B9/B8*B10 -> 0.033520356 | C11: 1990 USD / vkt | D11: Same as calculation for input value for 2030
A13: GCAM Input for "IRA_45W_light-truck_tax-credit" in 2025 | B13: =-B11 -> -0.033520356 | C13: 1990 USD / vkt | D13: This will the same in for all states and DC in GCAM-USA, and the value of the tax-credit will be the same in GCAM-global
A14: GCAM Input for "IRA_45W_light-truck_tax-credit" in 2030 | B14: =-B9 -> -0.033520356 | C14: 1990 USD / vkt | D14: This will the same in for all states and DC in GCAM-USA, and the value of the tax-credit will be the same in GCAM-global
A16: * for now, I remove the tax credit after 2032
